aos/__init__.py
aos/aos.py
aos/bind_matchers.py
aos/checker.py
aos/common.py
aos/dim.py
aos/eval_aos.py
aos/infer.py
aos/parser.py
aos/tfm.py
aos/type_matchers.py
aos/utils.py
aos-0.1.2.data/scripts/aos-infer
aos-0.1.2.dist-info/LICENSE.md
aos-0.1.2.dist-info/METADATA
aos-0.1.2.dist-info/WHEEL
aos-0.1.2.dist-info/top_level.txt
aos-0.1.2.dist-info/RECORD
