Metadata-Version: 2.1
Name: aos
Version: 0.1.2
Summary: A shape language for arbitrary data
Home-page: https://github.com/ofnote/aos
Author: Nishant Sinha
Author-email: nishant@offnote.co
License: Apache 2.0
Platform: POSIX
Classifier: Environment :: Console
Classifier: Intended Audience :: Developers
Classifier: License :: OSI Approved :: Apache Software License
Classifier: Operating System :: OS Independent
Classifier: Programming Language :: Python :: 3.6
Classifier: Programming Language :: Python :: 3.7
Classifier: Topic :: Software Development
Classifier: Topic :: Scientific/Engineering :: Artificial Intelligence
